LICENSE
MANIFEST.in
setup.py
lingua_podre/__init__.py
lingua_podre/opm.py
lingua_podre.egg-info/PKG-INFO
lingua_podre.egg-info/SOURCES.txt
lingua_podre.egg-info/dependency_links.txt
lingua_podre.egg-info/entry_points.txt
lingua_podre.egg-info/top_level.txt
lingua_podre/res/languages.json
lingua_podre/res/1000/README.md
lingua_podre/res/1000/afrikaans.txt
lingua_podre/res/1000/albanian.txt
lingua_podre/res/1000/arabic.txt
lingua_podre/res/1000/armenian.txt
lingua_podre/res/1000/azerbaijani.txt
lingua_podre/res/1000/basque.txt
lingua_podre/res/1000/belarusian.txt
lingua_podre/res/1000/bengali.txt
lingua_podre/res/1000/bosnian.txt
lingua_podre/res/1000/bulgarian.txt
lingua_podre/res/1000/catalan.txt
lingua_podre/res/1000/cebuano.txt
lingua_podre/res/1000/chichewa.txt
lingua_podre/res/1000/chinese.txt
lingua_podre/res/1000/corsican.txt
lingua_podre/res/1000/croatian.txt
lingua_podre/res/1000/czech.txt
lingua_podre/res/1000/danish.txt
lingua_podre/res/1000/dutch.txt
lingua_podre/res/1000/english.txt
lingua_podre/res/1000/esperanto.txt
lingua_podre/res/1000/estonian.txt
lingua_podre/res/1000/filipino.txt
lingua_podre/res/1000/finnish.txt
lingua_podre/res/1000/french.txt
lingua_podre/res/1000/frisian.txt
lingua_podre/res/1000/galician.txt
lingua_podre/res/1000/georgian.txt
lingua_podre/res/1000/german.txt
lingua_podre/res/1000/greek.txt
lingua_podre/res/1000/gujarati.txt
lingua_podre/res/1000/haitian.txt
lingua_podre/res/1000/hausa.txt
lingua_podre/res/1000/hawaiian.txt
lingua_podre/res/1000/hebrew.txt
lingua_podre/res/1000/hindi.txt
lingua_podre/res/1000/hmong.txt
lingua_podre/res/1000/hungarian.txt
lingua_podre/res/1000/icelandic.txt
lingua_podre/res/1000/igbo.txt
lingua_podre/res/1000/indonesian.txt
lingua_podre/res/1000/irish.txt
lingua_podre/res/1000/italian.txt
lingua_podre/res/1000/japanese.txt
lingua_podre/res/1000/javanese.txt
lingua_podre/res/1000/kannada.txt
lingua_podre/res/1000/kazakh.txt
lingua_podre/res/1000/khmer.txt
lingua_podre/res/1000/korean.txt
lingua_podre/res/1000/kurdish.txt
lingua_podre/res/1000/kyrgyz.txt
lingua_podre/res/1000/lao.txt
lingua_podre/res/1000/latin.txt
lingua_podre/res/1000/latvian.txt
